{
	"sources" : 
	[
		{
			"file" : "/home/ian/ttk/ParaView-v5.6.0/VTK/Web/Core/vtkDataEncoder.cxx"
		},
		{
			"file" : "/home/ian/ttk/ParaView-v5.6.0/VTK/Web/Core/vtkWebApplication.cxx"
		},
		{
			"file" : "/home/ian/ttk/ParaView-v5.6.0/VTK/Web/Core/vtkWebInteractionEvent.cxx"
		},
		{
			"file" : "/home/ian/ttk/ParaView-v5.6.0/VTK/Web/Core/vtkWebUtilities.cxx"
		},
		{
			"file" : "/home/ian/ttk/ParaView-v5.6.0/VTK/Web/Core/vtkObjectIdMap.cxx"
		},
		{
			"file" : "/home/ian/ttk/ParaView-v5.6.0/VTK/Web/Core/vtkDataEncoder.h"
		},
		{
			"file" : "/home/ian/ttk/ParaView-v5.6.0/VTK/Web/Core/vtkWebApplication.h"
		},
		{
			"file" : "/home/ian/ttk/ParaView-v5.6.0/VTK/Web/Core/vtkWebInteractionEvent.h"
		},
		{
			"file" : "/home/ian/ttk/ParaView-v5.6.0/VTK/Web/Core/vtkWebUtilities.h"
		},
		{
			"file" : "/home/ian/ttk/ParaView-v5.6.0/VTK/Web/Core/vtkObjectIdMap.h"
		},
		{
			"file" : "/home/ian/ttk/ParaView-v5.6.0/build/VTK/Web/Core/vtkWebCoreModule.h"
		}
	],
	"target" : 
	{
		"labels" : 
		[
			"vtkWebCore"
		],
		"name" : "vtkWebCore"
	}
}